LICENSE
MANIFEST.in
README.md
pyproject.toml
setup.py
src/halo_reader.egg-info/PKG-INFO
src/halo_reader.egg-info/SOURCES.txt
src/halo_reader.egg-info/dependency_links.txt
src/halo_reader.egg-info/entry_points.txt
src/halo_reader.egg-info/not-zip-safe
src/halo_reader.egg-info/requires.txt
src/halo_reader.egg-info/top_level.txt
src/haloboard/__init__.py
src/haloboard/app.py
src/haloboard/writer.py
src/haloboard/static/favicon.ico
src/haloboard/static/style.css
src/haloboard/templates/index.html
src/halodata/__init__.py
src/halodata/datasets.py
src/haloreader/__init__.py
src/haloreader/__main__.py
src/haloreader/attenuated_backscatter_coefficient.py
src/haloreader/attribute.py
src/haloreader/background_correction.py
src/haloreader/cli.py
src/haloreader/exceptions.py
src/haloreader/grammar_header.lark
src/haloreader/halo.py
src/haloreader/metadata.py
src/haloreader/py.typed
src/haloreader/read.py
src/haloreader/scantype.py
src/haloreader/screen.py
src/haloreader/transformer.py
src/haloreader/type_guards.py
src/haloreader/utils.py
src/haloreader/variable.py
src/haloreader/version.py
src/haloreader/background_reader/background_reader.c
src/haloreader/background_reader/background_reader.pyx
src/haloreader/data_reader/data_reader.c
src/haloreader/data_reader/data_reader.pyx
tests/test_bg_reader.py
tests/test_halo_reader.py