Metadata-Version: 2.1
Name: halo-reader
Version: 0.1.6
Summary: HALO Photonics wind doppler lidar file reader
Author-email: Niko Leskinen <niko.leskinen@fmi.fi>
License: MIT License
Project-URL: Homepage, https://github.com/actris-cloudnet/halo-reader
Project-URL: Repository, https://github.com/actris-cloudnet/halo-reader
Project-URL: Changelog, https://github.com/actris-cloudnet/halo-reader/blob/main/CHANGELOG.md
Project-URL: Bug Tracker, https://github.com/actris-cloudnet/halo-reader/issues
Classifier: Development Status :: 4 - Beta
Classifier: Programming Language :: Python :: 3
Classifier: Programming Language :: Python :: 3.10
Classifier: Programming Language :: Python :: 3.11
Classifier: License :: OSI Approved :: MIT License
Classifier: Intended Audience :: Science/Research
Classifier: Operating System :: OS Independent
Requires-Python: >=3.10
License-File: LICENSE
Requires-Dist: cython
Requires-Dist: numpy
Requires-Dist: lark
Requires-Dist: netCDF4
Requires-Dist: matplotlib
Requires-Dist: flask
Requires-Dist: requests
Requires-Dist: scikit-learn
Requires-Dist: scipy
Provides-Extra: dev
Requires-Dist: mypy; extra == "dev"
Requires-Dist: pytest; extra == "dev"
Requires-Dist: pytest-cov; extra == "dev"
Requires-Dist: black; extra == "dev"
Requires-Dist: flake8; extra == "dev"
Requires-Dist: pylint; extra == "dev"
Requires-Dist: autoflake; extra == "dev"
Requires-Dist: isort; extra == "dev"
Requires-Dist: pre-commit; extra == "dev"
Requires-Dist: types-requests; extra == "dev"
Requires-Dist: cfchecker; extra == "dev"
